{
  "metadata": {
    "digest_type": "comprehensive_multi_platform",
    "generated_at": "2025-07-31T17:45:00Z",
    "framework_version": "2.0.0",
    "total_items_considered": 8,
    "items_included": 6,
    "quality_threshold": 0.85,
    "personalization_active": true
  },
  "executive_summary": {
    "status": "ACTIVE",
    "system_health": "EXCELLENT",
    "health_percentage": 95,
    "total_items": 8,
    "high_quality_items": 6,
    "average_quality_score": 0.92,
    "recommendation": "Focus on software engineering trends and development tooling insights"
  },
  "priority_intelligence": [
    {
      "id": "software_engineering_trends",
      "title": "Software Engineering & Development Trends",
      "source": "YouTube Intelligence Network",
      "quality_score": 0.92,
      "topics": ["TypeScript", "React", "Software Architecture", "Development Tools"],
      "key_insights": [
        "Advanced TypeScript patterns and enterprise-scale implementations",
        "React ecosystem evolution and performance optimization strategies",
        "Modern development tooling and workflow enhancements",
        "Software engineering best practices and architectural decisions"
      ],
      "actionable_items": [
        "Review latest TypeScript advanced features for enterprise applications",
        "Investigate new React optimization techniques for production systems",
        "Evaluate emerging development tools for workflow improvement",
        "Consider architectural patterns discussed for current projects"
      ]
    },
    {
      "id": "system_infrastructure",
      "title": "System Infrastructure & Monitoring",
      "source": "Unified Intelligence System Health Reports",
      "quality_score": 0.88,
      "status": "OPERATIONAL",
      "metrics": {
        "youtube_monitoring": "ACTIVE",
        "content_processing": "OPERATIONAL",
        "knowledge_vault": "HEALTHY",
        "cross_platform": "FUNCTIONAL"
      },
      "recommendations": [
        "Continue current monitoring frequency",
        "Maintain content quality thresholds",
        "Monitor for new high-value sources",
        "Optimize processing workflows"
      ]
    }
  ],
  "platform_breakdown": {
    "youtube_intelligence": {
      "status": "HIGH_ACTIVITY",
      "channels_monitored": 6,
      "average_quality": 0.9,
      "top_sources": [
        {
          "name": "ThePrimeagen",
          "focus": "Software engineering insights, development practices",
          "preference_weight": 5.0
        },
        {
          "name": "Fireship",
          "focus": "Technology trends, development tools, programming tutorials",
          "preference_weight": 5.0
        }
      ]
    },
    "knowledge_vault": {
      "status": "SYNCHRONIZED",
      "databases_active": ["Content Intelligence", "Tools & Services"],
      "processing_state": "CURRENT",
      "recent_updates": [
        "User preferences optimized for technical content",
        "Cross-platform intelligence mapping enhanced",
        "Quality scoring algorithms refined",
        "Source discovery framework updated"
      ]
    }
  },
  "trending_topics": {
    "high_priority": [
      {
        "topic": "TypeScript Advanced Patterns",
        "score": 0.95,
        "description": "Enterprise-scale development"
      },
      {
        "topic": "React Performance Optimization",
        "score": 0.93,
        "description": "Production system enhancements"
      },
      {
        "topic": "Development Tooling Evolution",
        "score": 0.91,
        "description": "Workflow and productivity improvements"
      },
      {
        "topic": "Software Architecture Decisions",
        "score": 0.90,
        "description": "Modern design patterns and practices"
      }
    ],
    "emerging_trends": [
      {
        "topic": "AI-Assisted Development",
        "score": 0.87,
        "description": "Integration of AI tools in development workflows"
      },
      {
        "topic": "Infrastructure as Code",
        "score": 0.85,
        "description": "Modern deployment and infrastructure management"
      },
      {
        "topic": "Frontend Framework Evolution",
        "score": 0.83,
        "description": "Next-generation web development approaches"
      },
      {
        "topic": "Developer Experience Enhancement",
        "score": 0.82,
        "description": "Tools and practices for improved productivity"
      }
    ]
  },
  "system_health": {
    "core_metrics": {
      "intelligence_processing": "100% operational",
      "content_quality_filtering": "Active (0.7+ threshold)",
      "user_preference_application": "Functional",
      "cross_platform_synthesis": "Operational"
    },
    "monitoring_status": {
      "youtube_rss_feeds": "6/6 active",
      "content_processing_queue": "Empty",
      "knowledge_vault_sync": "Current",
      "system_health_checks": "All green"
    },
    "performance_indicators": {
      "processing_latency": "<30 seconds average",
      "content_accuracy": "95%+ verified",
      "preference_alignment": "High correlation",
      "discovery_success": "Daily high-value content"
    }
  },
  "recommendations": {
    "immediate_actions": [
      "Review TypeScript Content - Examine advanced patterns from ThePrimeagen analysis",
      "Evaluate React Optimizations - Consider performance techniques from Fireship insights",
      "Tool Assessment - Review recommended development tools for adoption",
      "Architecture Planning - Apply discussed patterns to current projects"
    ],
    "strategic_intelligence": [
      "Technology Adoption Planning - Develop roadmap for emerging tools and practices",
      "Team Knowledge Sharing - Disseminate key insights to development teams",
      "Process Optimization - Implement workflow improvements identified",
      "Continuous Learning - Schedule deeper dives into priority topics"
    ],
    "system_optimization": [
      "Source Expansion - Consider adding complementary intelligence sources",
      "Quality Refinement - Continue optimizing content scoring algorithms",
      "Personalization Enhancement - Fine-tune preference learning systems",
      "Cross-Platform Integration - Expand intelligence synthesis capabilities"
    ]
  },
  "sources": {
    "primary_sources": [
      "YouTube Intelligence Network: ThePrimeagen, Fireship channels",
      "System Health Monitoring: Unified Intelligence automation system",
      "Knowledge Vault: Content intelligence databases",
      "User Preferences: Personalized scoring and filtering system"
    ],
    "confidence_levels": {
      "content_quality_scores": "High confidence (verified algorithms)",
      "trend_analysis": "Medium-high confidence (pattern recognition)",
      "recommendations": "High confidence (user preference alignment)",
      "system_metrics": "Maximum confidence (direct measurement)"
    }
  },
  "next_digest": {
    "scheduled": "2025-08-01T17:45:00Z",
    "focus_areas": ["Software engineering trends", "Emerging technology adoption"],
    "expected_sources": ["YouTube intelligence", "System health updates", "New content discovery"],
    "enhancement": "Expanded cross-platform intelligence synthesis"
  }
}